chesspal_mcp_engine/__init__.py
chesspal_mcp_engine/config.py
chesspal_mcp_engine/engine_wrapper.py
chesspal_mcp_engine/health_server.py
chesspal_mcp_engine/logging_config.py
chesspal_mcp_engine/main.py
chesspal_mcp_engine/models.py
chesspal_mcp_engine/shutdown.py
chesspal_mcp_engine-0.3.0.dist-info/LICENSE
chesspal_mcp_engine-0.3.0.dist-info/METADATA
chesspal_mcp_engine-0.3.0.dist-info/WHEEL
chesspal_mcp_engine-0.3.0.dist-info/entry_points.txt
chesspal_mcp_engine-0.3.0.dist-info/RECORD
