Metadata-Version: 2.3
Name: chesspal-mcp-engine
Version: 0.3.0
Summary: ChessPal MCP Engine: A Stockfish-powered chess engine exposed via MCP.
License: GPL-3.0-or-later
Keywords: chess,stockfish,mcp,chesspal
Author: Your Name
Author-email: your.email@example.com
Requires-Python: >=3.10,<4.0
Classifier: Development Status :: 4 - Beta
Classifier: Intended Audience :: Developers
Classifier: License :: OSI Approved :: GNU General Public License v3 or later (GPLv3+)
Classifier: Programming Language :: Python :: 3
Classifier: Programming Language :: Python :: 3.10
Classifier: Programming Language :: Python :: 3.11
Classifier: Programming Language :: Python :: 3.12
Classifier: Programming Language :: Python :: 3.13
Classifier: Topic :: Games/Entertainment :: Board Games
Requires-Dist: fastapi (>=0.110.0,<0.111.0)
Requires-Dist: mcp[cli] (>=1.6,<2.0)
Requires-Dist: pydantic-settings (>=2.2.1,<3.0.0)
Requires-Dist: python-chess (>=1.999,<2.0)
Requires-Dist: setuptools (>=69.2.0,<70.0.0)
Requires-Dist: structlog (>=25.2.0,<26.0.0)
Requires-Dist: uvicorn[standard] (>=0.27.1,<0.28.0)
Project-URL: Repository, https://github.com/wilson-urdaneta/dylangames-mcp-chess-engine
